billionfong/__init__.py
billionfong/billionfong.py
billionfong/games.py
billionfong-1.2.6.dist-info/METADATA
billionfong-1.2.6.dist-info/RECORD
billionfong-1.2.6.dist-info/WHEEL
billionfong-1.2.6.dist-info/top_level.txt
