Metadata-Version: 2.1
Name: billionfong
Version: 1.2.6
Summary: Welcome to billionfong's playground
Home-page: https://www.billionfong.com/
Author: Billy Fong
Author-email: billionfong@billionfong.com
License: UNKNOWN
Download-URL: https://github.com/billionfong/Python_Package
Platform: UNKNOWN
